topsis_raghav_102303580/__init__.py
topsis_raghav_102303580/topsis.py
topsis_raghav_102303580-1.0.2.dist-info/METADATA
topsis_raghav_102303580-1.0.2.dist-info/WHEEL
topsis_raghav_102303580-1.0.2.dist-info/entry_points.txt
topsis_raghav_102303580-1.0.2.dist-info/top_level.txt
topsis_raghav_102303580-1.0.2.dist-info/RECORD
