Metadata-Version: 2.4
Name: topsis-raghav-102303580
Version: 1.0.2
Summary: TOPSIS implementation as a Python package
Author: Raghav
Author-email: raghavchhabra291984@gmail.com
Requires-Dist: pandas
Requires-Dist: numpy
Dynamic: author
Dynamic: author-email
Dynamic: description
Dynamic: description-content-type
Dynamic: requires-dist
Dynamic: summary
